[
	{
    		"label": "概览",
    		"translations": {
    			"en": "Introduction"
    		},
    		"link": "ai/overview/"
    },
    {
        		"label": "核心概念",
        		"translations": {
        			"en": "Concepts"
        		},
        		"link": "ai/concepts/"
	},
	 {
				"label": "快速开始",
				"translations": {
					"en": "Quick Start"
				},
				"link": "ai/get-started/"
	},
	{
				"label": "使用教程",
				"translations": {
					"en": "Tutorials"
				},
				"link": "ai/tutorials/",
				"autogenerate": {
					"directory": "tutorials"
				}
	},
	{
				"label": "最佳实践",
				"translations": {
					"en": "practices"
				},
				"link": "ai/practices/",
				"autogenerate": {
					"directory": "practices"
				}
	}

]